medusa_core/__init__.py
medusa_core/binary/Abstract.py
medusa_core/binary/BinaryRequest.py
medusa_core/binary/BinaryResponse.py
medusa_core/binary/__init__.py
medusa_core/exceptions/__init__.py
medusa_core/exceptions/binary/__init__.py
medusa_core/exceptions/server/__init__.py
medusa_core/server/Router.py
medusa_core/server/TcpServer.py
medusa_core/server/UdpServer.py
medusa_core/server/__init__.py
medusa_core-0.0.2.dist-info/AUTHORS.rst
medusa_core-0.0.2.dist-info/METADATA
medusa_core-0.0.2.dist-info/WHEEL
medusa_core-0.0.2.dist-info/top_level.txt
medusa_core-0.0.2.dist-info/RECORD
